remote_mcp_server/__init__.py
remote_mcp_server/config.py
remote_mcp_server/logger.py
remote_mcp_server/server.py
remote_mcp_server_new_new-0.1.1.dist-info/METADATA
remote_mcp_server_new_new-0.1.1.dist-info/WHEEL
remote_mcp_server_new_new-0.1.1.dist-info/RECORD
