Metadata-Version: 2.4
Name: remote_mcp_server_new_new
Version: 0.1.1
Summary: Remote MCP Server
Requires-Python: >=3.13
Requires-Dist: fastapi[standard]>=0.115.12
Requires-Dist: httpx>=0.28.1
Requires-Dist: mcp[cli]>=1.6.0
Requires-Dist: pydantic>=2.11.1
Requires-Dist: requests>=2.32.3
Requires-Dist: setuptools>=78.1.0
Requires-Dist: uvicorn[standard]>=0.34.0
